mm_downloader/__init__.py
mm_downloader/downloader.py
src/__init__.py
src/example.py
mm_download_img-0.1.1.dist-info/METADATA
mm_download_img-0.1.1.dist-info/WHEEL
mm_download_img-0.1.1.dist-info/top_level.txt
mm_download_img-0.1.1.dist-info/RECORD
