Metadata-Version: 2.1
Name: mm-download-img
Version: 0.1.1
Summary: A library to download image from s3
Author: Viet Nguyen Ba
Author-email: nbviet98@gmail.com
Classifier: Programming Language :: Python :: 3
Classifier: License :: OSI Approved :: MIT License
Classifier: Operating System :: OS Independent
Requires-Dist: opencv-python
